iDEA/EXT1.py
iDEA/EXT2.py
iDEA/EXT3.py
iDEA/EXT_cython.c
iDEA/EXT_cython.cpython-36m-darwin.so
iDEA/EXT_cython.pyx
iDEA/HF.py
iDEA/HYB.py
iDEA/LDA.py
iDEA/LDA_parameters.py
iDEA/NON.py
iDEA/RE.py
iDEA/RE_cython.c
iDEA/RE_cython.cpython-36m-darwin.so
iDEA/RE_cython.pyx
iDEA/__init__.py
iDEA/cli.py
iDEA/info.py
iDEA/input.py
iDEA/minimize.py
iDEA/mix.py
iDEA/parameters.py
iDEA/plot.py
iDEA/precondition.py
iDEA/results.py
iDEA/splash.py
iDEA/test_EXT1.py
iDEA/test_EXT2.py
iDEA/test_EXT3.py
iDEA/test_HF.py
iDEA/test_HYB.py
iDEA/test_LDA.py
iDEA/test_NON.py
iDEA/test_minimize.py
iDEA/test_mix.py
iDEA/test_result.py
idea_code-0.1.0a2.dist-info/METADATA
idea_code-0.1.0a2.dist-info/WHEEL
idea_code-0.1.0a2.dist-info/entry_points.txt
idea_code-0.1.0a2.dist-info/top_level.txt
idea_code-0.1.0a2.dist-info/RECORD
