Metadata-Version: 2.1
Name: idea-code
Version: 0.1.0a2
Summary: interacting Dynamic Electrons Approach
Home-page: http://www.cmt.york.ac.uk/group_info/idea_html/
Author: S. Adamson, J. Chapman, T. Durrant, R. Elmaslmane, M. Entwistle, R. Godby, M. Hodgson, P. Lillystone, A. Long, R. Oliver, J. Ramsden, E. Richardson, M. Smith, L. Talirz, J. Wetherell
License: MIT
Platform: UNKNOWN
Classifier: Development Status :: 3 - Alpha
Classifier: License :: OSI Approved :: MIT License
Classifier: Programming Language :: Python :: 3
Classifier: Programming Language :: Python :: 3.3
Classifier: Programming Language :: Python :: 3.4
Classifier: Programming Language :: Python :: 3.5
Requires-Dist: matplotlib (>=1.4)
Requires-Dist: numpy (>=1.10)
Requires-Dist: scipy (>=0.17)
Requires-Dist: cython (>=0.22)
Provides-Extra: doc
Requires-Dist: sphinx (>=1.4); extra == 'doc'
Requires-Dist: numpydoc; extra == 'doc'
Requires-Dist: jupyter; extra == 'doc'
Requires-Dist: nbsphinx; extra == 'doc'
Requires-Dist: coverage; extra == 'doc'
